pdc_logger/__init__.py
pdc_logger/client.py
pdc_logger/configuration.py
pdc_logger/exit_report.py
pdc_logger/logger.py
pdc_logger-1.1.0.dist-info/WHEEL
pdc_logger-1.1.0.dist-info/METADATA
pdc_logger-1.1.0.dist-info/RECORD
